Workbook
Name NativeTimeline_order_date: #N/A
Name Slicer_category_name: #N/A
Name Slicer_payment_method: #N/A
Name tbl_categories: categories!$A$2:$B$6
Name tbl_orders: Orders!$A$2:$E$9
Name tbl_products: Products!$A$2:$D$11

Sheet Customers
A1: customer_id | B1: first_name | C1: last_name | D1: city | E1: registration_date
A2: 39 | B2: William | C2: Anderson | D2: Chicago | E2: 45313
A3: 38 | B3: Ava | C3: Taylor | D3: Houston | E3: 45311
A4: 37 | B4: James | C4: Moore | D4: Denver | E4: 45308
A5: 36 | B5: Olivia | C5: Wilson | D5: Miami | E5: 45306
A6: 35 | B6: Daniel | C6: Miller | D6: Dallas | E6: 45305
A7: 34 | B7: Sophia | C7: Davis | D7: Seattle | E7: 45303
A8: 33 | B8: Michael | C8: Brown | D8: Boston | E8: 45301
A9: 32 | B9: Emma | C9: Johnson | D9: Chicago | E9: 45298
A10: 31 | B10: John | C10: Smith | D10: New York | E10: 45296
A11: 30 | B11: Grace | C11: Green | D11: Denver | E11: 45029
A12: 29 | B12: Aiden | C12: Scott | D12: Boston | E12: 45026
A13: 28 | B13: Scarlett | C13: Wright | D13: Seattle | E13: 45024
... A40: 1 | B40: John | C40: Smith | D40: New York | E40: 44941

Sheet categories
A1: category_id | B1: category_name
A2: 1 | B2: Laptops
A3: 2 | B3: Smartphones
A4: 3 | B4: Accessories
A5: 4 | B5: Monitors
A6: 5 | B6: Gaming

Sheet Products
A1: product_id | B1: product_name | C1: category_id | D1: price | E1: category_name
A2: 1 | B2: MacBook Air M3 | C2: 1 | D2: 1200 | E2: =_xlfn.XLOOKUP(C2,categories!A:A, categories!B:B ) -> Laptops
A3: 2 | B3: ThinkPad T14 | C3: 1 | D3: 1100 | E3: =_xlfn.XLOOKUP(C3,categories!A:A, categories!B:B ) -> Laptops
A4: 3 | B4: iPhone 15 | C4: 2 | D4: 990 | E4: =_xlfn.XLOOKUP(C4,categories!A:A, categories!B:B ) -> Smartphones
A5: 4 | B5: Samsung S24 | C5: 2 | D5: 950 | E5: =_xlfn.XLOOKUP(C5,categories!A:A, categories!B:B ) -> Smartphones
A6: 9 | B6: PlayStation 5 | C6: 5 | D6: 550 | E6: =_xlfn.XLOOKUP(C6,categories!A:A, categories!B:B ) -> Gaming
A7: 10 | B7: Xbox Series X | C7: 5 | D7: 530 | E7: =_xlfn.XLOOKUP(C7,categories!A:A, categories!B:B ) -> Gaming
A8: 8 | B8: LG Ultrawide | C8: 4 | D8: 450
A9: 7 | B9: Dell 27 Monitor | C9: 4 | D9: 280
A10: 5 | B10: Mechanical Keyboard | C10: 3 | D10: 120
A11: 6 | B11: Wireless Mouse | C11: 3 | D11: 50

Sheet Detail1
A1: Details for Average of unit_price - customer_id: 2
A3: order_item_id | B3: order_id | C3: product_id | D3: quantity | E3: unit_price | F3: customer_id | G3: revenue | H3: product_name | I3: category_name | J3: category_id | K3: payment_status
A4: 8 | B4: 7 | C4: 2 | D4: 1 | E4: 1100 | F4: 2 | G4: 1100 | H4: ThinkPad T14 | I4: Laptops | J4: 1 | K4: Paid
A5: 3 | B5: 2 | C5: 3 | D5: 1 | E5: 999 | F5: 2 | G5: 999 | H5: iPhone 15 | I5: Smartphones | J5: 2 | K5: Paid

Sheet Detail2
A1: Details for Average of unit_price - customer_id: 1
A3: order_item_id | B3: order_id | C3: product_id | D3: quantity | E3: unit_price | F3: customer_id | G3: revenue | H3: product_name | I3: category_name | J3: category_id | K3: payment_status
A4: 1 | B4: 1 | C4: 1 | D4: 1 | E4: 1200 | F4: 1 | G4: 1200 | H4: MacBook Air M3 | I4: Laptops | J4: 1 | K4: Paid
A5: 2 | B5: 1 | C5: 5 | D5: 1 | E5: 120 | F5: 1 | G5: 120 | H5: Mechanical Keyboard | I5: Accessories | J5: 3 | K5: Paid
A6: 7 | B6: 6 | C6: 6 | D6: 2 | E6: 50 | F6: 1 | G6: 100 | H6: Wireless Mouse | I6: Accessories | J6: 3 | K6: Paid

Sheet Detail3
A1: Details for Average of unit_price - customer_id: 2
A3: order_item_id | B3: order_id | C3: product_id | D3: quantity | E3: unit_price | F3: customer_id | G3: revenue | H3: product_name | I3: category_name | J3: category_id | K3: payment_status
A4: 8 | B4: 7 | C4: 2 | D4: 1 | E4: 1100 | F4: 2 | G4: 1100 | H4: ThinkPad T14 | I4: Laptops | J4: 1 | K4: Paid
A5: 3 | B5: 2 | C5: 3 | D5: 1 | E5: 999 | F5: 2 | G5: 999 | H5: iPhone 15 | I5: Smartphones | J5: 2 | K5: Paid

Sheet customer_pivot_practice
A3: Row Labels | B3: Sum of revenue | D3: Row Labels | E3: Sum of revenue
A4: 1 | B4: 1420 | D4: 2 | E4: 2099
A5: 2 | B5: 2099 | D5: 1 | E5: 1420
A6: 3 | B6: 560 | D6: 4 | E6: 950
A7: 4 | B7: 950 | D7: 3 | E7: 560
A8: 5 | B8: 550 | D8: 5 | E8: 550
A9: 6 | B9: 530 | D9: 6 | E9: 530
A10: Grand Total | B10: 6109 | D10: Grand Total | E10: 6109
A18: Row Labels | B18: Sum of revenue | D18: Row Labels | E18: Sum of quantity
A19: 2 | B19: 2099 | D19: 1 | E19: 4
A20: 1 | B20: 1420 | D20: 2 | E20: 2
A21: 4 | B21: 950 | D21: 3 | E21: 2
A22: 3 | B22: 560 | D22: 4 | E22: 1
A23: 5 | B23: 550 | D23: 5 | E23: 1
A24: 6 | B24: 530 | D24: 6 | E24: 1
A25: Grand Total | B25: 6109 | D25: Grand Total | E25: 11
A30: Row Labels | B30: Sum of revenue | D30: Row Labels | E30: Sum of revenue
A31: 2 | B31: 2099 | D31: 2 | E31: 2099
A32: 1 | B32: 1420 | D32: 1 | E32: 1420
A33: 4 | B33: 950 | D33: 4 | E33: 950
A34: 3 | B34: 560 | D34: 3 | E34: 560
A35: 5 | B35: 550 | D35: 5 | E35: 550
A36: 6 | B36: 530 | D36: 6 | E36: 530
A37: Grand Total | B37: 6109 | D37: Grand Total | E37: 6109

Sheet dashboard

Sheet Product_pivot_practice
A3: Row Labels | B3: Sum of revenue
A4: Wireless Mouse | B4: 100
A5: Mechanical Keyboard | B5: 120
A6: Xbox Series X | B6: 530
A7: PlayStation 5 | B7: 550
A8: Dell 27 Monitor | B8: 560
A9: Samsung S24 | B9: 950
A10: iPhone 15 | B10: 999
A11: ThinkPad T14 | B11: 1100
A12: MacBook Air M3 | B12: 1200
A13: Grand Total | B13: 6109

Sheet category_pivot_practice
A3: Row Labels | B3: Sum of revenue
A4: Accessories | B4: 220
A5: Gaming | B5: 1080
A6: Laptops | B6: 2300
A7: Monitors | B7: 560
A8: Smartphones | B8: 1949
A9: Grand Total | B9: 6109

Sheet Detail4
A1: Details for Count of payment_method - payment_method: Card
A3: order_item_id | B3: order_id | C3: product_id | D3: quantity | E3: unit_price | F3: customer_id | G3: revenue | H3: product_name | I3: category_name | J3: category_id | K3: payment_status | L3: payment_method
A4: 1 | B4: 1 | C4: 1 | D4: 1 | E4: 1200 | F4: 1 | G4: 1200 | H4: MacBook Air M3 | I4: Laptops | J4: 1 | K4: Paid | L4: Card
A5: 2 | B5: 1 | C5: 5 | D5: 1 | E5: 120 | F5: 1 | G5: 120 | H5: Mechanical Keyboard | I5: Accessories | J5: 3 | K5: Paid | L5: Card
A6: 9 | B6: 8 | C6: 10 | D6: 1 | E6: 530 | F6: 6 | G6: 530 | H6: Xbox Series X | I6: Gaming | J6: 5 | K6: Paid | L6: Card
A7: 4 | B7: 3 | C7: 7 | D7: 2 | E7: 280 | F7: 3 | G7: 560 | H7: Dell 27 Monitor | I7: Monitors | J7: 4 | K7: Paid | L7: Card
A8: 6 | B8: 5 | C8: 9 | D8: 1 | E8: 550 | F8: 5 | G8: 550 | H8: PlayStation 5 | I8: Gaming | J8: 5 | K8: Cancelled | L8: Card

Sheet payments_pivot_practice
A3: Payment method | B3: Sum of order_id
A4: Card | B4: 18
A5: Cash | B5: 8
A6: Transfer | B6: 11
A7: Grand Total | B7: 37
A21: Payment method | B21: Count of payment_status
A22: Cancelled | B22: 1
A23: Paid | B23: 8
A24: Grand Total | B24: 9

Sheet Orders
A1: order_id | B1: customer_id | C1: order_date | D1: status | E1: amount | H1: first_name | I1: last_name | J1: city | L1: first_name | M1: last_name | N1: city | P1: first_name | Q1: last_name | R1: city
A2: 6 | B2: 1 | C2: 45379 | D2: Completed | E2: 0 | H2: =_xlfn.XLOOKUP(B2,tbl_customers[customer_id],tbl_customers[first_name]) -> John | I2: =_xlfn.XLOOKUP(B2,tbl_customers[customer_id],tbl_customers[last_name]) -> Smith | J2: =_xlfn.XLOOKUP(B2,tbl_customers[customer_id],tbl_customers[city]) -> New York | L2: =VLOOKUP(B2,Customers!A:D,2,FALSE) -> John | M2: =VLOOKUP(B2,Customers!A:D,3,FALSE) -> Smith | N2: =VLOOKUP(B2,Customers!A:D,4,FALSE) -> New York | P2: =INDEX(Customers!B:B,MATCH(B2,Customers!A:A,0)) -> John | Q2: =INDEX(Customers!C:C,MATCH(B2,Customers!A:A,0)) -> Smith | R2: =INDEX(Customers!D:D,MATCH(B2,Customers!A:A,0)) -> New York
A3: 7 | B3: 2 | C3: 45392 | D3: Cancelled | E3: 0 | H3: =_xlfn.XLOOKUP(B3,tbl_customers[customer_id],tbl_customers[first_name]) -> Emma | I3: =_xlfn.XLOOKUP(B3,tbl_customers[customer_id],tbl_customers[last_name]) -> Johnson | J3: =_xlfn.XLOOKUP(B3,tbl_customers[customer_id],tbl_customers[city]) -> Chicago | L3: =VLOOKUP(B3,Customers!A:D,2,FALSE) -> Emma | M3: =VLOOKUP(B3,Customers!A:D,3,FALSE) -> Johnson | N3: =VLOOKUP(B3,Customers!A:D,4,FALSE) -> Chicago | P3: =INDEX(Customers!B:B,MATCH(B3,Customers!A:A,0)) -> Emma | Q3: =INDEX(Customers!C:C,MATCH(B3,Customers!A:A,0)) -> Johnson | R3: =INDEX(Customers!D:D,MATCH(B3,Customers!A:A,0)) -> Chicago
A4: 8 | B4: 6 | C4: 45411 | D4: Completed | E4: 0 | H4: =_xlfn.XLOOKUP(B4,tbl_customers[customer_id],tbl_customers[first_name]) -> Olivia | I4: =_xlfn.XLOOKUP(B4,tbl_customers[customer_id],tbl_customers[last_name]) -> Wilson | J4: =_xlfn.XLOOKUP(B4,tbl_customers[customer_id],tbl_customers[city]) -> Dallas | L4: =VLOOKUP(B4,Customers!A:D,2,FALSE) -> Olivia | M4: =VLOOKUP(B4,Customers!A:D,3,FALSE) -> Wilson | N4: =VLOOKUP(B4,Customers!A:D,4,FALSE) -> Dallas | P4: =INDEX(Customers!B:B,MATCH(B4,Customers!A:A,0)) -> Olivia | Q4: =INDEX(Customers!C:C,MATCH(B4,Customers!A:A,0)) -> Wilson | R4: =INDEX(Customers!D:D,MATCH(B4,Customers!A:A,0)) -> Dallas
A5: 1 | B5: 1 | C5: 45296 | D5: Completed | E5: 120.50 | H5: =_xlfn.XLOOKUP(B5,tbl_customers[customer_id],tbl_customers[first_name]) -> John | I5: =_xlfn.XLOOKUP(B5,tbl_customers[customer_id],tbl_customers[last_name]) -> Smith | J5: =_xlfn.XLOOKUP(B5,tbl_customers[customer_id],tbl_customers[city]) -> New York | L5: =VLOOKUP(B5,Customers!A:D,2,FALSE) -> John | M5: =VLOOKUP(B5,Customers!A:D,3,FALSE) -> Smith | N5: =VLOOKUP(B5,Customers!A:D,4,FALSE) -> New York | P5: =INDEX(Customers!B:B,MATCH(B5,Customers!A:A,0)) -> John | Q5: =INDEX(Customers!C:C,MATCH(B5,Customers!A:A,0)) -> Smith | R5: =INDEX(Customers!D:D,MATCH(B5,Customers!A:A,0)) -> New York
A6: 2 | B6: 2 | C6: 45308 | D6: Completed | E6: 75.00 | H6: =_xlfn.XLOOKUP(B6,tbl_customers[customer_id],tbl_customers[first_name]) -> Emma | I6: =_xlfn.XLOOKUP(B6,tbl_customers[customer_id],tbl_customers[last_name]) -> Johnson | J6: =_xlfn.XLOOKUP(B6,tbl_customers[customer_id],tbl_customers[city]) -> Chicago | L6: =VLOOKUP(B6,Customers!A:D,2,FALSE) -> Emma | M6: =VLOOKUP(B6,Customers!A:D,3,FALSE) -> Johnson | N6: =VLOOKUP(B6,Customers!A:D,4,FALSE) -> Chicago | P6: =INDEX(Customers!B:B,MATCH(B6,Customers!A:A,0)) -> Emma | Q6: =INDEX(Customers!C:C,MATCH(B6,Customers!A:A,0)) -> Johnson | R6: =INDEX(Customers!D:D,MATCH(B6,Customers!A:A,0)) -> Chicago
A7: 3 | B7: 3 | C7: 45325 | D7: Completed | E7: 210.99 | H7: =_xlfn.XLOOKUP(B7,tbl_customers[customer_id],tbl_customers[first_name]) -> Michael | I7: =_xlfn.XLOOKUP(B7,tbl_customers[customer_id],tbl_customers[last_name]) -> Brown | J7: =_xlfn.XLOOKUP(B7,tbl_customers[customer_id],tbl_customers[city]) -> Los Angeles | L7: =VLOOKUP(B7,Customers!A:D,2,FALSE) -> Michael | M7: =VLOOKUP(B7,Customers!A:D,3,FALSE) -> Brown | N7: =VLOOKUP(B7,Customers!A:D,4,FALSE) -> Los Angeles | P7: =INDEX(Customers!B:B,MATCH(B7,Customers!A:A,0)) -> Michael | Q7: =INDEX(Customers!C:C,MATCH(B7,Customers!A:A,0)) -> Brown | R7: =INDEX(Customers!D:D,MATCH(B7,Customers!A:A,0)) -> Los Angeles
A8: 4 | B8: 4 | C8: 45347 | D8: Pending | E8: 55.50 | H8: =_xlfn.XLOOKUP(B8,tbl_customers[customer_id],tbl_customers[first_name]) -> Sophia | I8: =_xlfn.XLOOKUP(B8,tbl_customers[customer_id],tbl_customers[last_name]) -> Davis | J8: =_xlfn.XLOOKUP(B8,tbl_customers[customer_id],tbl_customers[city]) -> Houston | L8: =VLOOKUP(B8,Customers!A:D,2,FALSE) -> Sophia | M8: =VLOOKUP(B8,Customers!A:D,3,FALSE) -> Davis | N8: =VLOOKUP(B8,Customers!A:D,4,FALSE) -> Houston | P8: =INDEX(Customers!B:B,MATCH(B8,Customers!A:A,0)) -> Sophia | Q8: =INDEX(Customers!C:C,MATCH(B8,Customers!A:A,0)) -> Davis | R8: =INDEX(Customers!D:D,MATCH(B8,Customers!A:A,0)) -> Houston
A9: 5 | B9: 5 | C9: 45363 | D9: Completed | E9: 330.00 | H9: =_xlfn.XLOOKUP(B9,tbl_customers[customer_id],tbl_customers[first_name]) -> Daniel | I9: =_xlfn.XLOOKUP(B9,tbl_customers[customer_id],tbl_customers[last_name]) -> Miller | J9: =_xlfn.XLOOKUP(B9,tbl_customers[customer_id],tbl_customers[city]) -> Phoenix | L9: =VLOOKUP(B9,Customers!A:D,2,FALSE) -> Daniel | M9: =VLOOKUP(B9,Customers!A:D,3,FALSE) -> Miller | N9: =VLOOKUP(B9,Customers!A:D,4,FALSE) -> Phoenix | P9: =INDEX(Customers!B:B,MATCH(B9,Customers!A:A,0)) -> Daniel | Q9: =INDEX(Customers!C:C,MATCH(B9,Customers!A:A,0)) -> Miller | R9: =INDEX(Customers!D:D,MATCH(B9,Customers!A:A,0)) -> Phoenix

Sheet Order_items
A1: order_item_id | B1: order_id | C1: product_id | D1: quantity | E1: unit_price | F1: customer_id | G1: revenue | H1: product_name | I1: category_name | J1: category_id | K1: payment_status | L1: payment_method | M1: order_date
A2: 1 | B2: 1 | C2: 1 | D2: 1 | E2: 1200 | F2: =_xlfn.XLOOKUP(B2,Orders!A:A,Orders!B:B) -> 1 | G2: =D2*E2 -> 1200 | H2: =_xlfn.XLOOKUP(C2,tbl_product[product_id],tbl_product[product_name]) -> MacBook Air M3 | I2: =_xlfn.XLOOKUP(J2, categories!A:A, categories!B:B) -> Laptops | J2: =_xlfn.XLOOKUP(C2,Products!A:A,Products!C:C) -> 1 | K2: =_xlfn.XLOOKUP(B2,Payments!A:A,Payments!D:D) -> Paid | L2: =_xlfn.XLOOKUP(B2,Payments!A:A,Payments!C:C) -> Card | M2: =_xlfn.XLOOKUP(B2,Orders!A:A,Orders!C:C) -> 45296
A3: 2 | B3: 1 | C3: 5 | D3: 1 | E3: 120 | F3: =_xlfn.XLOOKUP(B3,Orders!A:A,Orders!B:B) -> 1 | G3: =--D3*--E3 -> 120 | H3: =_xlfn.XLOOKUP(C3,tbl_product[product_id],tbl_product[product_name]) -> Mechanical Keyboard | I3: =_xlfn.XLOOKUP(J3, categories!A:A, categories!B:B) -> Accessories | J3: =_xlfn.XLOOKUP(C3,Products!A:A,Products!C:C) -> 3 | K3: =_xlfn.XLOOKUP(B3,Payments!A:A,Payments!D:D) -> Paid | L3: =_xlfn.XLOOKUP(B3,Payments!A:A,Payments!C:C) -> Card | M3: =_xlfn.XLOOKUP(B3,Orders!A:A,Orders!C:C) -> 45296
A4: 3 | B4: 2 | C4: 3 | D4: 1 | E4: 999 | F4: =_xlfn.XLOOKUP(B4,Orders!A:A,Orders!B:B) -> 2 | G4: =D4*E4 -> 999 | H4: =_xlfn.XLOOKUP(C4,tbl_product[product_id],tbl_product[product_name]) -> iPhone 15 | I4: =_xlfn.XLOOKUP(J4, categories!A:A, categories!B:B) -> Smartphones | J4: =_xlfn.XLOOKUP(C4,Products!A:A,Products!C:C) -> 2 | K4: =_xlfn.XLOOKUP(B4,Payments!A:A,Payments!D:D) -> Paid | L4: =_xlfn.XLOOKUP(B4,Payments!A:A,Payments!C:C) -> Cash | M4: =_xlfn.XLOOKUP(B4,Orders!A:A,Orders!C:C) -> 45308
A5: 4 | B5: 3 | C5: 7 | D5: 2 | E5: 280 | F5: =_xlfn.XLOOKUP(B5,Orders!A:A,Orders!B:B) -> 3 | G5: =D5*E5 -> 560 | H5: =_xlfn.XLOOKUP(C5,tbl_product[product_id],tbl_product[product_name]) -> Dell 27 Monitor | I5: =_xlfn.XLOOKUP(J5, categories!A:A, categories!B:B) -> Monitors | J5: =_xlfn.XLOOKUP(C5,Products!A:A,Products!C:C) -> 4 | K5: =_xlfn.XLOOKUP(B5,Payments!A:A,Payments!D:D) -> Paid | L5: =_xlfn.XLOOKUP(B5,Payments!A:A,Payments!C:C) -> Card | M5: =_xlfn.XLOOKUP(B5,Orders!A:A,Orders!C:C) -> 45325
A6: 5 | B6: 4 | C6: 4 | D6: 1 | E6: 950 | F6: =_xlfn.XLOOKUP(B6,Orders!A:A,Orders!B:B) -> 4 | G6: =D6*E6 -> 950 | H6: =_xlfn.XLOOKUP(C6,tbl_product[product_id],tbl_product[product_name]) -> Samsung S24 | I6: =_xlfn.XLOOKUP(J6, categories!A:A, categories!B:B) -> Smartphones | J6: =_xlfn.XLOOKUP(C6,Products!A:A,Products!C:C) -> 2 | K6: =_xlfn.XLOOKUP(B6,Payments!A:A,Payments!D:D) -> Paid | L6: =_xlfn.XLOOKUP(B6,Payments!A:A,Payments!C:C) -> Transfer | M6: =_xlfn.XLOOKUP(B6,Orders!A:A,Orders!C:C) -> 45347
A7: 6 | B7: 5 | C7: 9 | D7: 1 | E7: 550 | F7: =_xlfn.XLOOKUP(B7,Orders!A:A,Orders!B:B) -> 5 | G7: =D7*E7 -> 550 | H7: =_xlfn.XLOOKUP(C7,tbl_product[product_id],tbl_product[product_name]) -> PlayStation 5 | I7: =_xlfn.XLOOKUP(J7, categories!A:A, categories!B:B) -> Gaming | J7: =_xlfn.XLOOKUP(C7,Products!A:A,Products!C:C) -> 5 | K7: =_xlfn.XLOOKUP(B7,Payments!A:A,Payments!D:D) -> Cancelled | L7: =_xlfn.XLOOKUP(B7,Payments!A:A,Payments!C:C) -> Card | M7: =_xlfn.XLOOKUP(B7,Orders!A:A,Orders!C:C) -> 45363
A8: 7 | B8: 6 | C8: 6 | D8: 2 | E8: 50 | F8: =_xlfn.XLOOKUP(B8,Orders!A:A,Orders!B:B) -> 1 | G8: =D8*E8 -> 100 | H8: =_xlfn.XLOOKUP(C8,tbl_product[product_id],tbl_product[product_name]) -> Wireless Mouse | I8: =_xlfn.XLOOKUP(J8, categories!A:A, categories!B:B) -> Accessories | J8: =_xlfn.XLOOKUP(C8,Products!A:A,Products!C:C) -> 3 | K8: =_xlfn.XLOOKUP(B8,Payments!A:A,Payments!D:D) -> Paid | L8: =_xlfn.XLOOKUP(B8,Payments!A:A,Payments!C:C) -> Cash | M8: =_xlfn.XLOOKUP(B8,Orders!A:A,Orders!C:C) -> 45379
A9: 8 | B9: 7 | C9: 2 | D9: 1 | E9: 1100 | F9: =_xlfn.XLOOKUP(B9,Orders!A:A,Orders!B:B) -> 2 | G9: =D9*E9 -> 1100 | H9: =_xlfn.XLOOKUP(C9,tbl_product[product_id],tbl_product[product_name]) -> ThinkPad T14 | I9: =_xlfn.XLOOKUP(J9, categories!A:A, categories!B:B) -> Laptops | J9: =_xlfn.XLOOKUP(C9,Products!A:A,Products!C:C) -> 1 | K9: =_xlfn.XLOOKUP(B9,Payments!A:A,Payments!D:D) -> Paid | L9: =_xlfn.XLOOKUP(B9,Payments!A:A,Payments!C:C) -> Transfer | M9: =_xlfn.XLOOKUP(B9,Orders!A:A,Orders!C:C) -> 45392
A10: 9 | B10: 8 | C10: 10 | D10: 1 | E10: 530 | F10: =_xlfn.XLOOKUP(B10,Orders!A:A,Orders!B:B) -> 6 | G10: =D10*E10 -> 530 | H10: =_xlfn.XLOOKUP(C10,tbl_product[product_id],tbl_product[product_name]) -> Xbox Series X | I10: =_xlfn.XLOOKUP(J10, categories!A:A, categories!B:B) -> Gaming | J10: =_xlfn.XLOOKUP(C10,Products!A:A,Products!C:C) -> 5 | K10: =_xlfn.XLOOKUP(B10,Payments!A:A,Payments!D:D) -> Paid | L10: =_xlfn.XLOOKUP(B10,Payments!A:A,Payments!C:C) -> Card | M10: =_xlfn.XLOOKUP(B10,Orders!A:A,Orders!C:C) -> 45411
B14: price | C14: category_id | E14: product_name | F14: price | G14: category_id | I14: product_name | J14: price | K14: category_id
B15: =_xlfn.XLOOKUP(C2,tbl_product[product_id],tbl_product[price]) -> 1200 | C15: =_xlfn.XLOOKUP(C2,tbl_product[product_id],tbl_product[category_id]) -> 1 | E15: =VLOOKUP(C2,Products!A:D,2,FALSE) -> MacBook Air M3 | F15: =VLOOKUP(C2,Products!A:D,4,FALSE) -> 1200 | G15: =VLOOKUP(C2,Products!A:D,3,FALSE) -> 1 | I15: =INDEX(Products!B:B,MATCH(C2,Products!A:A,0)) -> MacBook Air M3 | J15: =INDEX(Products!D:D,MATCH(C2,Products!A:A,0)) -> 1200 | K15: =INDEX(Products!C:C,MATCH(C2,Products!A:A,0)) -> 1
B16: =_xlfn.XLOOKUP(C3,tbl_product[product_id],tbl_product[price]) -> 120 | C16: =_xlfn.XLOOKUP(C3,tbl_product[product_id],tbl_product[category_id]) -> 3 | E16: =VLOOKUP(C3,Products!A:D,2,FALSE) -> Mechanical Keyboard | F16: =VLOOKUP(C3,Products!A:D,4,FALSE) -> 120 | G16: =VLOOKUP(C3,Products!A:D,3,FALSE) -> 3 | I16: =INDEX(Products!B:B,MATCH(C3,Products!A:A,0)) -> Mechanical Keyboard | J16: =INDEX(Products!D:D,MATCH(C3,Products!A:A,0)) -> 120 | K16: =INDEX(Products!C:C,MATCH(C3,Products!A:A,0)) -> 3
B17: =_xlfn.XLOOKUP(C4,tbl_product[product_id],tbl_product[price]) -> 990 | C17: =_xlfn.XLOOKUP(C4,tbl_product[product_id],tbl_product[category_id]) -> 2 | E17: =VLOOKUP(C4,Products!A:D,2,FALSE) -> iPhone 15 | F17: =VLOOKUP(C4,Products!A:D,4,FALSE) -> 990 | G17: =VLOOKUP(C4,Products!A:D,3,FALSE) -> 2 | I17: =INDEX(Products!B:B,MATCH(C4,Products!A:A,0)) -> iPhone 15 | J17: =INDEX(Products!D:D,MATCH(C4,Products!A:A,0)) -> 990 | K17: =INDEX(Products!C:C,MATCH(C4,Products!A:A,0)) -> 2
B18: =_xlfn.XLOOKUP(C5,tbl_product[product_id],tbl_product[price]) -> 280 | C18: =_xlfn.XLOOKUP(C5,tbl_product[product_id],tbl_product[category_id]) -> 4 | E18: =VLOOKUP(C5,Products!A:D,2,FALSE) -> Dell 27 Monitor | F18: =VLOOKUP(C5,Products!A:D,4,FALSE) -> 280 | G18: =VLOOKUP(C5,Products!A:D,3,FALSE) -> 4 | I18: =INDEX(Products!B:B,MATCH(C5,Products!A:A,0)) -> Dell 27 Monitor | J18: =INDEX(Products!D:D,MATCH(C5,Products!A:A,0)) -> 280 | K18: =INDEX(Products!C:C,MATCH(C5,Products!A:A,0)) -> 4
B19: =_xlfn.XLOOKUP(C6,tbl_product[product_id],tbl_product[price]) -> 950 | C19: =_xlfn.XLOOKUP(C6,tbl_product[product_id],tbl_product[category_id]) -> 2 | E19: =VLOOKUP(C6,Products!A:D,2,FALSE) -> Samsung S24 | F19: =VLOOKUP(C6,Products!A:D,4,FALSE) -> 950 | G19: =VLOOKUP(C6,Products!A:D,3,FALSE) -> 2 | I19: =INDEX(Products!B:B,MATCH(C6,Products!A:A,0)) -> Samsung S24 | J19: =INDEX(Products!D:D,MATCH(C6,Products!A:A,0)) -> 950 | K19: =INDEX(Products!C:C,MATCH(C6,Products!A:A,0)) -> 2
B20: =_xlfn.XLOOKUP(C7,tbl_product[product_id],tbl_product[price]) -> 550 | C20: =_xlfn.XLOOKUP(C7,tbl_product[product_id],tbl_product[category_id]) -> 5 | E20: =VLOOKUP(C7,Products!A:D,2,FALSE) -> PlayStation 5 | F20: =VLOOKUP(C7,Products!A:D,4,FALSE) -> 550 | G20: =VLOOKUP(C7,Products!A:D,3,FALSE) -> 5 | I20: =INDEX(Products!B:B,MATCH(C7,Products!A:A,0)) -> PlayStation 5 | J20: =INDEX(Products!D:D,MATCH(C7,Products!A:A,0)) -> 550 | K20: =INDEX(Products!C:C,MATCH(C7,Products!A:A,0)) -> 5
B21: =_xlfn.XLOOKUP(C8,tbl_product[product_id],tbl_product[price]) -> 50 | C21: =_xlfn.XLOOKUP(C8,tbl_product[product_id],tbl_product[category_id]) -> 3 | E21: =VLOOKUP(C8,Products!A:D,2,FALSE) -> Wireless Mouse | F21: =VLOOKUP(C8,Products!A:D,4,FALSE) -> 50 | G21: =VLOOKUP(C8,Products!A:D,3,FALSE) -> 3 | I21: =INDEX(Products!B:B,MATCH(C8,Products!A:A,0)) -> Wireless Mouse | J21: =INDEX(Products!D:D,MATCH(C8,Products!A:A,0)) -> 50 | K21: =INDEX(Products!C:C,MATCH(C8,Products!A:A,0)) -> 3 | AJ21: {=W2:AJ21} -> 0
B22: =_xlfn.XLOOKUP(C9,tbl_product[product_id],tbl_product[price]) -> 1100 | C22: =_xlfn.XLOOKUP(C9,tbl_product[product_id],tbl_product[category_id]) -> 1 | E22: =VLOOKUP(C9,Products!A:D,2,FALSE) -> ThinkPad T14 | F22: =VLOOKUP(C9,Products!A:D,4,FALSE) -> 1100 | G22: =VLOOKUP(C9,Products!A:D,3,FALSE) -> 1 | I22: =INDEX(Products!B:B,MATCH(C9,Products!A:A,0)) -> ThinkPad T14 | J22: =INDEX(Products!D:D,MATCH(C9,Products!A:A,0)) -> 1100 | K22: =INDEX(Products!C:C,MATCH(C9,Products!A:A,0)) -> 1
B23: =_xlfn.XLOOKUP(C10,tbl_product[product_id],tbl_product[price]) -> 530 | C23: =_xlfn.XLOOKUP(C10,tbl_product[product_id],tbl_product[category_id]) -> 5 | E23: =VLOOKUP(C10,Products!A:D,2,FALSE) -> Xbox Series X | F23: =VLOOKUP(C10,Products!A:D,4,FALSE) -> 530 | G23: =VLOOKUP(C10,Products!A:D,3,FALSE) -> 5 | I23: =INDEX(Products!B:B,MATCH(C10,Products!A:A,0)) -> Xbox Series X | J23: =INDEX(Products!D:D,MATCH(C10,Products!A:A,0)) -> 530 | K23: =INDEX(Products!C:C,MATCH(C10,Products!A:A,0)) -> 5

Sheet Payments
A1: payment_id | B1: order_id | C1: payment_method | D1: payment_status | E1: payment_date
A2: 1 | B2: 1 | C2: Card | D2: Paid | E2: 45296
A3: 2 | B3: 2 | C3: Cash | D3: Paid | E3: 45303
A4: 3 | B4: 3 | C4: Card | D4: Paid | E4: 45324
A5: 4 | B5: 4 | C5: Transfer | D5: Paid | E5: 45340
A6: 5 | B6: 5 | C6: Card | D6: Cancelled | E6: 45361
A7: 6 | B7: 6 | C7: Cash | D7: Paid | E7: 45376
A8: 7 | B8: 7 | C8: Transfer | D8: Paid | E8: 45394
A9: 8 | B9: 8 | C9: Card | D9: Paid | E9: 45410

Sheet Practice
A1: Customer | B1: Revenue | C1: SUM | D1: AVG | E1: MAX | F1: MIN | G1: COUNT | H1: SEGMENT | I1: SEGMENT 2
A2: Emma | B2: 2099 | C2: =SUM(B2:B5) -> 4699 | D2: =AVERAGE(B2:B5) -> 1174.75 | E2: =MAX(B2:B5) -> 2099 | F2: =MIN(B2:B5) -> 500 | G2: =COUNT(B2:B5) -> 4 | H2: =IF(B2>1000,"VIP","Regular") -> VIP | I2: {=_xlfn.IFS(B2>1500,"Premium",B2>1000,"VIP",TRUE,"Regular")} -> Premium
A3: Anna | B3: 1200 | H3: =IF(B3>1000,"VIP","Regular") -> VIP | I3: {=_xlfn.IFS(B3>1500,"Premium",B3>1000,"VIP",TRUE,"Regular")} -> VIP
A4: Alex | B4: 900 | H4: =IF(B4>1000,"VIP","Regular") -> Regular | I4: {=_xlfn.IFS(B4>1500,"Premium",B4>1000,"VIP",TRUE,"Regular")} -> Regular
A5: John | B5: 500 | H5: =IF(B5>1000,"VIP","Regular") -> Regular | I5: {=_xlfn.IFS(B5>1500,"Premium",B5>1000,"VIP",TRUE,"Regular")} -> Regular
